{
"categorys":["All","App","Tempelate","MiniProject"],
"portfolio":[
    {
        "id":14,
        "title":"Shoping-Card",
        "category":"Tempelate",
        "yearOf":"2023",
        "languages":["TypeScript"],
        "packeages":["React-js","React-BootStarp"],
        "url":"https://goldshopcard.netlify.app/",
        "coverImg":"/images/portfolio/gold-shop-card.png",
        "desc":"",
        "images":[]
    },
    {
        "id":0,
        "title":"My-Resume",
        "category":"Tempelate",
        "yearOf":"2023",
        "languages":["JavaScript"],
        "packeages":["Next-js","Tailwind css","animate.css"],
        "url":"https://ramin-majidi.netlify.app/",
        "coverImg":"/images/portfolio/my-site.png",
        "desc":"",
        "images":[]
    },
    {
        "id":1,
        "title":"signature-maker",
        "category":"App",
        "yearOf":"2023",
        "languages":["HTML","CSS","JavaScript"],
        "packeages":["React-js","react-signature-canvas"],
        "url":"https://signature-maker.netlify.app/",
        "coverImg":"/images/portfolio/signature-maker.png",
        "desc":"",
        "images":[]
    },
    {
        "id":2,
        "title":"online-azmon",
        "category":"Tempelate",
        "yearOf":"2022",
        "languages":["HTML","CSS","JavaScript"],
        "packeages":["React-js","API","axios"],
        "url":"https://onlineazmon.netlify.app/",
        "coverImg":"/images/portfolio/onlineazmon.png",
        "desc":"",
        "images":[]
    },
    {
        "id":3,
        "title":"multi-calendar",
        "category":"App",
        "yearOf":"2023",
        "languages":["TypeScript","CSS"],
        "packeages":["React-js","react-multi-date-picker"],
        "url":"https://multicalendar.netlify.app/",
        "coverImg":"/images/portfolio/multi-calendar.png",
        "desc":"",
        "images":[]
    },
    {
        "id":4,
        "title":"pelates-studio",
        "category":"Tempelate",
        "yearOf":"2022",
        "languages":["HTML","CSS","JavaScript"],
        "packeages":["animate.css"],
        "url":"https://pelates.netlify.app/",
        "coverImg":"/images/portfolio/pelatesSite.png",
        "desc":"",
        "images":[]
    },
    {
        "id":5,
        "title":"bmi-App",
        "category":"App",
        "yearOf":"2021",
        "languages":["HTML","CSS","JavaScript"],
        "packeages":[],
        "url":"https://bmi-app-js.netlify.app/",
        "coverImg":"/images/portfolio/bmiApp.png",
        "desc":"",
        "images":[]
    },
    {
        "id":6,
        "title":"noghteh-khat-Game",
        "category":"MiniProject",
        "yearOf":"2022",
        "languages":["HTML","CSS","JavaScript"],
        "packeages":[],
        "url":"https://noghteh-khat.netlify.app/",
        "coverImg":"/images/portfolio/noghteGame.png",
        "desc":"",
        "images":[]
    },
    {
        "id":7,
        "title":"abohava-App",
        "category":"App",
        "yearOf":"2022",
        "languages":["HTML","CSS","JavaScript"],
        "packeages":["API"],
        "url":"https://abohava-js.netlify.app/",
        "coverImg":"/images/portfolio/abohavaApp.png",
        "desc":"",
        "images":[]
    },
    {
        "id":8,
        "title":"ToDoList-App",
        "category":"App",
        "yearOf":"2022",
        "languages":["HTML","CSS","JavaScript"],
        "packeages":[],
        "url":"https://todo-ad.netlify.app/",
        "coverImg":"/images/portfolio/todolistApp.png",
        "desc":"",
        "images":[]
    },
    {
        "id":9,
        "title":"doz-Game",
        "category":"MiniProject",
        "yearOf":"2021",
        "languages":["HTML","CSS","JavaScript"],
        "packeages":["formik","animate.css","axios"],
        "url":"https://dozgame.netlify.app/",
        "coverImg":"/images/portfolio/dozGame.png",
        "desc":"",
        "images":[]
    },
    {
        "id":10,
        "title":"car-gallery",
        "category":"Tempelate",
        "yearOf":"2022",
        "languages":["HTML","CSS"],
        "packeages":["BootStrap"],
        "url":"https://cargalley.netlify.app/",
        "coverImg":"/images/portfolio/car-gallery.png",
        "desc":"",
        "images":[]
    },
    {
        "id":11,
        "title":"motor-gallery",
        "category":"Tempelate",
        "yearOf":"2022",
        "languages":["HTML","CSS"],
        "packeages":["BootStrap"],
        "url":"https://motorgallery.netlify.app/",
        "coverImg":"/images/portfolio/motor-gallery.png",
        "desc":"",
        "images":[]
    },
    {
        "id":12,
        "title":"aks-kadeh",
        "category":"Tempelate",
        "yearOf":"2022",
        "languages":["jsx","CSS"],
        "packeages":["BootStrap","react-js","axios","formik","API"],
        "url":"https://akskadeh.netlify.app/",
        "coverImg":"/images/portfolio/aks-kadeh.jpg",
        "desc":"سایت عکس کده یک سایت برای دانلود عکس های با کیفیت در زمینه های مختلف است . این سایت به عنوان یکی از پروژه های عملی دوره ری اکت سایت کدیاد توسط رامین مجیدی طراحی و کدنویسی شده است .",
        "images":[]
    }
]
}
